master_mind/__init__.py
master_mind/__main__.py
master_mind/__version__.py
master_mind/builtin_courses.py
master_mind/configuration.py
master_mind/datasets.py
master_mind/discovery.py
master_mind/install.py
master_mind/plugin.py
master_mind/utils.py
master_mind/cli/__init__.py
master_mind/cli/rl.py
master_mind/requirements/adl.txt
master_mind/requirements/deep.txt
master_mind/requirements/deepl.txt
master_mind/requirements/llm.txt
master_mind/requirements/rital.txt
master_mind/requirements/rl.txt
master_mind/rld/__init__.py
master_mind/rld/stk.py
master_mind/rld/stk_graph.py
master_mind/teaching/__init__.py
master_mind/teaching/hf.py
master_mind/teaching/utils.py
su_master_mind-2026.1.31.dist-info/METADATA
su_master_mind-2026.1.31.dist-info/WHEEL
su_master_mind-2026.1.31.dist-info/entry_points.txt
su_master_mind-2026.1.31.dist-info/RECORD
