Metadata-Version: 2.4
Name: su_master_mind
Version: 2026.1.31
Summary: Sorbonne University Master MIND dependency & dataset manager
Author-email: Benjamin Piwowarski <benjamin@piwowarski.fr>
Requires-Python: >=3.10
Requires-Dist: appdirs>=1.4
Requires-Dist: cached-property>=1.5; python_version <= '3.7'
Requires-Dist: click>=8
Requires-Dist: importlib-resources>=6; python_version <= '3.8'
Requires-Dist: packaging>=23
Requires-Dist: requests>=2
Provides-Extra: adl
Requires-Dist: datamaestro-image>=2025.9.21; extra == 'adl'
Requires-Dist: datamaestro-text>=2026.1.1; extra == 'adl'
Requires-Dist: datamaestro>=1.5; extra == 'adl'
Requires-Dist: experimaestro>=1.11.1; extra == 'adl'
Requires-Dist: future; extra == 'adl'
Requires-Dist: ipython; extra == 'adl'
Requires-Dist: ipywidgets; extra == 'adl'
Requires-Dist: jupyter; extra == 'adl'
Requires-Dist: jupyterlab; extra == 'adl'
Requires-Dist: jupyterlab-empinken-extension; extra == 'adl'
Requires-Dist: jupyterlab-widgets; extra == 'adl'
Requires-Dist: matplotlib; extra == 'adl'
Requires-Dist: pandas; extra == 'adl'
Requires-Dist: scikit-image>=0.24.0; extra == 'adl'
Requires-Dist: scikit-learn; extra == 'adl'
Requires-Dist: seaborn; extra == 'adl'
Requires-Dist: tensorboard>=2.10; extra == 'adl'
Requires-Dist: tensorflow-macos>=2.10; (platform_machine == 'arm64' and sys_platform == 'darwin') and extra == 'adl'
Requires-Dist: tensorflow>=2.10; (platform_machine != 'arm64' or sys_platform != 'darwin') and extra == 'adl'
Requires-Dist: torch>=2.5; extra == 'adl'
Requires-Dist: torchvision; extra == 'adl'
Provides-Extra: deep
Requires-Dist: datamaestro-image>=2025.9.21; extra == 'deep'
Requires-Dist: datamaestro-text>=2026.1.1; extra == 'deep'
Requires-Dist: datamaestro>=1.5; extra == 'deep'
Requires-Dist: experimaestro>=1.11.1; extra == 'deep'
Requires-Dist: future; extra == 'deep'
Requires-Dist: ipython; extra == 'deep'
Requires-Dist: ipywidgets; extra == 'deep'
Requires-Dist: jupyter; extra == 'deep'
Requires-Dist: jupyterlab; extra == 'deep'
Requires-Dist: jupyterlab-empinken-extension; extra == 'deep'
Requires-Dist: jupyterlab-widgets; extra == 'deep'
Requires-Dist: matplotlib; extra == 'deep'
Requires-Dist: pandas; extra == 'deep'
Requires-Dist: scikit-learn; extra == 'deep'
Requires-Dist: seaborn; extra == 'deep'
Requires-Dist: tensorboard>=2.10; extra == 'deep'
Requires-Dist: tensorflow-macos>=2.10; (platform_machine == 'arm64' and sys_platform == 'darwin') and extra == 'deep'
Requires-Dist: tensorflow>=2.10; (platform_machine != 'arm64' or sys_platform != 'darwin') and extra == 'deep'
Requires-Dist: torch>=2.5; extra == 'deep'
Requires-Dist: torchvision; extra == 'deep'
Provides-Extra: deepl
Requires-Dist: bs4; extra == 'deepl'
Requires-Dist: conllu; extra == 'deepl'
Requires-Dist: datamaestro-image>=2025.9.21; extra == 'deepl'
Requires-Dist: datamaestro-text>=2026.1.1; extra == 'deepl'
Requires-Dist: datamaestro>=1.5; extra == 'deepl'
Requires-Dist: datasets>=2.7.0; extra == 'deepl'
Requires-Dist: einops; extra == 'deepl'
Requires-Dist: experimaestro>=1.11.1; extra == 'deepl'
Requires-Dist: future; extra == 'deepl'
Requires-Dist: ipython; extra == 'deepl'
Requires-Dist: ipywidgets; extra == 'deepl'
Requires-Dist: jupyter; extra == 'deepl'
Requires-Dist: jupyterlab; extra == 'deepl'
Requires-Dist: jupyterlab-empinken-extension; extra == 'deepl'
Requires-Dist: jupyterlab-widgets; extra == 'deepl'
Requires-Dist: matplotlib; extra == 'deepl'
Requires-Dist: networkx; extra == 'deepl'
Requires-Dist: optuna; extra == 'deepl'
Requires-Dist: pandas; extra == 'deepl'
Requires-Dist: pytorch-lightning; extra == 'deepl'
Requires-Dist: scikit-learn; extra == 'deepl'
Requires-Dist: seaborn; extra == 'deepl'
Requires-Dist: sentencepiece; extra == 'deepl'
Requires-Dist: spacy; extra == 'deepl'
Requires-Dist: tensorboard>=2.10; extra == 'deepl'
Requires-Dist: tensorflow-macos>=2.10; (platform_machine == 'arm64' and sys_platform == 'darwin') and extra == 'deepl'
Requires-Dist: tensorflow>=2.10; (platform_machine != 'arm64' or sys_platform != 'darwin') and extra == 'deepl'
Requires-Dist: torch>=2.5; extra == 'deepl'
Requires-Dist: torchvision; extra == 'deepl'
Requires-Dist: transformers; extra == 'deepl'
Provides-Extra: llm
Requires-Dist: su-master-mind-llm<2026.9.1,>=2025.9.1; extra == 'llm'
Provides-Extra: rital
Requires-Dist: datamaestro-image>=2025.9.21; extra == 'rital'
Requires-Dist: datamaestro-text>=2026.1.1; extra == 'rital'
Requires-Dist: datamaestro>=1.5; extra == 'rital'
Requires-Dist: experimaestro-ir>=0.6.1; extra == 'rital'
Requires-Dist: experimaestro>=1.11.1; extra == 'rital'
Requires-Dist: future; extra == 'rital'
Requires-Dist: ipython; extra == 'rital'
Requires-Dist: ipywidgets; extra == 'rital'
Requires-Dist: jupyter; extra == 'rital'
Requires-Dist: jupyterlab; extra == 'rital'
Requires-Dist: jupyterlab-empinken-extension; extra == 'rital'
Requires-Dist: jupyterlab-widgets; extra == 'rital'
Requires-Dist: matplotlib; extra == 'rital'
Requires-Dist: pandas; extra == 'rital'
Requires-Dist: pyserini; extra == 'rital'
Requires-Dist: scikit-learn; extra == 'rital'
Requires-Dist: seaborn; extra == 'rital'
Requires-Dist: tensorboard>=2.10; extra == 'rital'
Requires-Dist: tensorflow-macos>=2.10; (platform_machine == 'arm64' and sys_platform == 'darwin') and extra == 'rital'
Requires-Dist: tensorflow>=2.10; (platform_machine != 'arm64' or sys_platform != 'darwin') and extra == 'rital'
Requires-Dist: torch>=2.5; extra == 'rital'
Requires-Dist: torchvision; extra == 'rital'
Provides-Extra: rl
Requires-Dist: bbrl-utils>=1.1.1; extra == 'rl'
Requires-Dist: box2d; extra == 'rl'
Requires-Dist: box2d-kengz; extra == 'rl'
Requires-Dist: dash>=3; extra == 'rl'
Requires-Dist: datamaestro-image>=2025.9.21; extra == 'rl'
Requires-Dist: datamaestro-text>=2026.1.1; extra == 'rl'
Requires-Dist: datamaestro>=1.5; extra == 'rl'
Requires-Dist: experimaestro>=1.11.1; extra == 'rl'
Requires-Dist: future; extra == 'rl'
Requires-Dist: ipyreact>=0.4.0; extra == 'rl'
Requires-Dist: ipython; extra == 'rl'
Requires-Dist: ipywidgets; extra == 'rl'
Requires-Dist: jupyter; extra == 'rl'
Requires-Dist: jupyterlab; extra == 'rl'
Requires-Dist: jupyterlab-empinken-extension; extra == 'rl'
Requires-Dist: jupyterlab-widgets; extra == 'rl'
Requires-Dist: matplotlib; extra == 'rl'
Requires-Dist: mazemdp>=1.2.11; extra == 'rl'
Requires-Dist: moviepy; extra == 'rl'
Requires-Dist: pandas; extra == 'rl'
Requires-Dist: pyglet<2; extra == 'rl'
Requires-Dist: pystk2-gymnasium>=0.7.9; extra == 'rl'
Requires-Dist: scikit-learn; extra == 'rl'
Requires-Dist: seaborn; extra == 'rl'
Requires-Dist: tensorboard>=2.10; extra == 'rl'
Requires-Dist: tensorflow-macos>=2.10; (platform_machine == 'arm64' and sys_platform == 'darwin') and extra == 'rl'
Requires-Dist: tensorflow>=2.10; (platform_machine != 'arm64' or sys_platform != 'darwin') and extra == 'rl'
Requires-Dist: torch>=2.5; extra == 'rl'
Requires-Dist: torchdiffeq; extra == 'rl'
Requires-Dist: torchvision; extra == 'rl'
